[
  {
    "id": "cmksui3h4000511fc3ojy9l37",
    "name": "Men Shirts Product 1",
    "slug": "men-shirts-product-1",
    "description": "This is a high-quality Men Shirts Product 1 made from premium materials. Perfect for any occasion.",
    "categoryId": "cmksj65o10003mmox16czwo5b",
    "isFeatured": false,
    "isBestSeller": false,
    "isActive": true,
    "createdAt": "2026-01-24T21:52:22.551Z",
    "updatedAt": "2026-01-24T21:52:22.551Z",
    "basePrice": "1176",
    "isOffer": false,
    "artisanImage": null,
    "artisanStory": null,
    "careInstructions": null,
    "fabric": null,
    "occasion": null,
    "origin": null,
    "weave": null,
    "metaDescription": null,
    "metaTitle": null,
    "category": {
      "id": "cmksj65o10003mmox16czwo5b",
      "name": "Shirts",
      "slug": "men-shirts",
      "description": "Shirts for Men",
      "image": null,
      "parentId": "cmksj65b70001mmoxod3uz2mm",
      "createdAt": "2026-01-24T16:35:09.736Z",
      "updatedAt": "2026-01-24T16:35:09.736Z"
    }
  },
  {
    "id": "cmksui48r000e11fcmse8elfr",
    "name": "Men T-Shirts Product 1",
    "slug": "men-t-shirts-product-1",
    "description": "This is a high-quality Men T-Shirts Product 1 made from premium materials. Perfect for any occasion.",
    "categoryId": "cmksj65wo0005mmoxs7nsgzsl",
    "isFeatured": false,
    "isBestSeller": false,
    "isActive": true,
    "createdAt": "2026-01-24T21:52:23.547Z",
    "updatedAt": "2026-01-24T21:52:23.547Z",
    "basePrice": "1488",
    "isOffer": false,
    "artisanImage": null,
    "artisanStory": null,
    "careInstructions": null,
    "fabric": null,
    "occasion": null,
    "origin": null,
    "weave": null,
    "metaDescription": null,
    "metaTitle": null,
    "category": {
      "id": "cmksj65wo0005mmoxs7nsgzsl",
      "name": "T-Shirts",
      "slug": "men-t-shirts",
      "description": "T-Shirts for Men",
      "image": null,
      "parentId": "cmksj65b70001mmoxod3uz2mm",
      "createdAt": "2026-01-24T16:35:10.056Z",
      "updatedAt": "2026-01-24T16:35:10.056Z"
    }
  },
  {
    "id": "cmksui4tx000n11fckz2pu419",
    "name": "Men Jeans Product 1",
    "slug": "men-jeans-product-1",
    "description": "This is a high-quality Men Jeans Product 1 made from premium materials. Perfect for any occasion.",
    "categoryId": "cmksj66490007mmoxnzvjbq11",
    "isFeatured": false,
    "isBestSeller": true,
    "isActive": true,
    "createdAt": "2026-01-24T21:52:24.308Z",
    "updatedAt": "2026-01-24T21:52:24.308Z",
    "basePrice": "665",
    "isOffer": false,
    "artisanImage": null,
    "artisanStory": null,
    "careInstructions": null,
    "fabric": null,
    "occasion": null,
    "origin": null,
    "weave": null,
    "metaDescription": null,
    "metaTitle": null,
    "category": {
      "id": "cmksj66490007mmoxnzvjbq11",
      "name": "Jeans",
      "slug": "men-jeans",
      "description": "Jeans for Men",
      "image": null,
      "parentId": "cmksj65b70001mmoxod3uz2mm",
      "createdAt": "2026-01-24T16:35:10.329Z",
      "updatedAt": "2026-01-24T16:35:10.329Z"
    }
  },
  {
    "id": "cmksui5eq000w11fculiqtvq7",
    "name": "Men Trousers Product 1",
    "slug": "men-trousers-product-1",
    "description": "This is a high-quality Men Trousers Product 1 made from premium materials. Perfect for any occasion.",
    "categoryId": "cmksj66be0009mmoxlimqx4hd",
    "isFeatured": false,
    "isBestSeller": false,
    "isActive": true,
    "createdAt": "2026-01-24T21:52:25.058Z",
    "updatedAt": "2026-01-24T21:52:25.058Z",
    "basePrice": "1433",
    "isOffer": false,
    "artisanImage": null,
    "artisanStory": null,
    "careInstructions": null,
    "fabric": null,
    "occasion": null,
    "origin": null,
    "weave": null,
    "metaDescription": null,
    "metaTitle": null,
    "category": {
      "id": "cmksj66be0009mmoxlimqx4hd",
      "name": "Trousers",
      "slug": "men-trousers",
      "description": "Trousers for Men",
      "image": null,
      "parentId": "cmksj65b70001mmoxod3uz2mm",
      "createdAt": "2026-01-24T16:35:10.586Z",
      "updatedAt": "2026-01-24T16:35:10.586Z"
    }
  },
  {
    "id": "cmksui5z2001511fcay1jj2jb",
    "name": "Men Ethnic Wear Product 1",
    "slug": "men-ethnic-wear-product-1",
    "description": "This is a high-quality Men Ethnic Wear Product 1 made from premium materials. Perfect for any occasion.",
    "categoryId": "cmksj66it000bmmoxb5r1by5m",
    "isFeatured": false,
    "isBestSeller": true,
    "isActive": true,
    "createdAt": "2026-01-24T21:52:25.790Z",
    "updatedAt": "2026-01-24T21:52:25.790Z",
    "basePrice": "2039",
    "isOffer": false,
    "artisanImage": null,
    "artisanStory": null,
    "careInstructions": null,
    "fabric": null,
    "occasion": null,
    "origin": null,
    "weave": null,
    "metaDescription": null,
    "metaTitle": null,
    "category": {
      "id": "cmksj66it000bmmoxb5r1by5m",
      "name": "Ethnic Wear",
      "slug": "men-ethnic-wear",
      "description": "Ethnic Wear for Men",
      "image": null,
      "parentId": "cmksj65b70001mmoxod3uz2mm",
      "createdAt": "2026-01-24T16:35:10.853Z",
      "updatedAt": "2026-01-24T16:35:10.853Z"
    }
  },
  {
    "id": "cmksui6je001e11fclwxet504",
    "name": "Men Innerwear Product 1",
    "slug": "men-innerwear-product-1",
    "description": "This is a high-quality Men Innerwear Product 1 made from premium materials. Perfect for any occasion.",
    "categoryId": "cmksj66ri000dmmoxg47dicu3",
    "isFeatured": false,
    "isBestSeller": false,
    "isActive": true,
    "createdAt": "2026-01-24T21:52:26.521Z",
    "updatedAt": "2026-01-24T21:52:26.521Z",
    "basePrice": "1084",
    "isOffer": false,
    "artisanImage": null,
    "artisanStory": null,
    "careInstructions": null,
    "fabric": null,
    "occasion": null,
    "origin": null,
    "weave": null,
    "metaDescription": null,
    "metaTitle": null,
    "category": {
      "id": "cmksj66ri000dmmoxg47dicu3",
      "name": "Innerwear",
      "slug": "men-innerwear",
      "description": "Innerwear for Men",
      "image": null,
      "parentId": "cmksj65b70001mmoxod3uz2mm",
      "createdAt": "2026-01-24T16:35:11.166Z",
      "updatedAt": "2026-01-24T16:35:11.166Z"
    }
  },
  {
    "id": "cmksui7a1001o11fciss72xb1",
    "name": "Women Sarees Product 1",
    "slug": "women-sarees-product-1",
    "description": "This is a high-quality Women Sarees Product 1 made from premium materials. Perfect for any occasion.",
    "categoryId": "cmksj676c000gmmoxzyx5fxss",
    "isFeatured": false,
    "isBestSeller": true,
    "isActive": true,
    "createdAt": "2026-01-24T21:52:27.481Z",
    "updatedAt": "2026-01-24T21:52:27.481Z",
    "basePrice": "2424",
    "isOffer": false,
    "artisanImage": null,
    "artisanStory": null,
    "careInstructions": null,
    "fabric": null,
    "occasion": null,
    "origin": null,
    "weave": null,
    "metaDescription": null,
    "metaTitle": null,
    "category": {
      "id": "cmksj676c000gmmoxzyx5fxss",
      "name": "Sarees",
      "slug": "women-sarees",
      "description": "Sarees for Women",
      "image": null,
      "parentId": "cmksj66yy000emmoxu9r98xtz",
      "createdAt": "2026-01-24T16:35:11.701Z",
      "updatedAt": "2026-01-24T16:35:11.701Z"
    }
  },
  {
    "id": "cmksui7v6001x11fce995lmnu",
    "name": "Women Kurtas & Kurtis Product 1",
    "slug": "women-kurtas-and-kurtis-product-1",
    "description": "This is a high-quality Women Kurtas & Kurtis Product 1 made from premium materials. Perfect for any occasion.",
    "categoryId": "cmksj67du000immox0zqvj8z0",
    "isFeatured": false,
    "isBestSeller": true,
    "isActive": true,
    "createdAt": "2026-01-24T21:52:28.242Z",
    "updatedAt": "2026-01-24T21:52:28.242Z",
    "basePrice": "1762",
    "isOffer": false,
    "artisanImage": null,
    "artisanStory": null,
    "careInstructions": null,
    "fabric": null,
    "occasion": null,
    "origin": null,
    "weave": null,
    "metaDescription": null,
    "metaTitle": null,
    "category": {
      "id": "cmksj67du000immox0zqvj8z0",
      "name": "Kurtas & Kurtis",
      "slug": "women-kurtas-and-kurtis",
      "description": "Kurtas & Kurtis for Women",
      "image": null,
      "parentId": "cmksj66yy000emmoxu9r98xtz",
      "createdAt": "2026-01-24T16:35:11.971Z",
      "updatedAt": "2026-01-24T16:35:11.971Z"
    }
  },
  {
    "id": "cmksui8g4002611fcv0nqtf6k",
    "name": "Women Lehengas Product 1",
    "slug": "women-lehengas-product-1",
    "description": "This is a high-quality Women Lehengas Product 1 made from premium materials. Perfect for any occasion.",
    "categoryId": "cmksj67ky000kmmoxso9yi3c2",
    "isFeatured": false,
    "isBestSeller": false,
    "isActive": true,
    "createdAt": "2026-01-24T21:52:28.995Z",
    "updatedAt": "2026-01-24T21:52:28.995Z",
    "basePrice": "2159",
    "isOffer": false,
    "artisanImage": null,
    "artisanStory": null,
    "careInstructions": null,
    "fabric": null,
    "occasion": null,
    "origin": null,
    "weave": null,
    "metaDescription": null,
    "metaTitle": null,
    "category": {
      "id": "cmksj67ky000kmmoxso9yi3c2",
      "name": "Lehengas",
      "slug": "women-lehengas",
      "description": "Lehengas for Women",
      "image": null,
      "parentId": "cmksj66yy000emmoxu9r98xtz",
      "createdAt": "2026-01-24T16:35:12.226Z",
      "updatedAt": "2026-01-24T16:35:12.226Z"
    }
  },
  {
    "id": "cmksui90a002f11fc69woqsws",
    "name": "Women Jeans & Jeggings Product 1",
    "slug": "women-jeans-and-jeggings-product-1",
    "description": "This is a high-quality Women Jeans & Jeggings Product 1 made from premium materials. Perfect for any occasion.",
    "categoryId": "cmksj67ry000mmmoxab1qv10b",
    "isFeatured": false,
    "isBestSeller": false,
    "isActive": true,
    "createdAt": "2026-01-24T21:52:29.722Z",
    "updatedAt": "2026-01-24T21:52:29.722Z",
    "basePrice": "2016",
    "isOffer": false,
    "artisanImage": null,
    "artisanStory": null,
    "careInstructions": null,
    "fabric": null,
    "occasion": null,
    "origin": null,
    "weave": null,
    "metaDescription": null,
    "metaTitle": null,
    "category": {
      "id": "cmksj67ry000mmmoxab1qv10b",
      "name": "Jeans & Jeggings",
      "slug": "women-jeans-and-jeggings",
      "description": "Jeans & Jeggings for Women",
      "image": null,
      "parentId": "cmksj66yy000emmoxu9r98xtz",
      "createdAt": "2026-01-24T16:35:12.478Z",
      "updatedAt": "2026-01-24T16:35:12.478Z"
    }
  },
  {
    "id": "cmksui9kk002o11fcnbl2h9gx",
    "name": "Women Tops & Tees Product 1",
    "slug": "women-tops-and-tees-product-1",
    "description": "This is a high-quality Women Tops & Tees Product 1 made from premium materials. Perfect for any occasion.",
    "categoryId": "cmksj67zo000ommoxdk14il26",
    "isFeatured": false,
    "isBestSeller": true,
    "isActive": true,
    "createdAt": "2026-01-24T21:52:30.451Z",
    "updatedAt": "2026-01-24T21:52:30.451Z",
    "basePrice": "1346",
    "isOffer": false,
    "artisanImage": null,
    "artisanStory": null,
    "careInstructions": null,
    "fabric": null,
    "occasion": null,
    "origin": null,
    "weave": null,
    "metaDescription": null,
    "metaTitle": null,
    "category": {
      "id": "cmksj67zo000ommoxdk14il26",
      "name": "Tops & Tees",
      "slug": "women-tops-and-tees",
      "description": "Tops & Tees for Women",
      "image": null,
      "parentId": "cmksj66yy000emmoxu9r98xtz",
      "createdAt": "2026-01-24T16:35:12.756Z",
      "updatedAt": "2026-01-24T16:35:12.756Z"
    }
  },
  {
    "id": "cmksuia57002x11fcjf8das2q",
    "name": "Women Lingerie Product 1",
    "slug": "women-lingerie-product-1",
    "description": "This is a high-quality Women Lingerie Product 1 made from premium materials. Perfect for any occasion.",
    "categoryId": "cmksj686v000qmmox6yji3nl7",
    "isFeatured": false,
    "isBestSeller": false,
    "isActive": true,
    "createdAt": "2026-01-24T21:52:31.195Z",
    "updatedAt": "2026-01-24T21:52:31.195Z",
    "basePrice": "578",
    "isOffer": false,
    "artisanImage": null,
    "artisanStory": null,
    "careInstructions": null,
    "fabric": null,
    "occasion": null,
    "origin": null,
    "weave": null,
    "metaDescription": null,
    "metaTitle": null,
    "category": {
      "id": "cmksj686v000qmmox6yji3nl7",
      "name": "Lingerie",
      "slug": "women-lingerie",
      "description": "Lingerie for Women",
      "image": null,
      "parentId": "cmksj66yy000emmoxu9r98xtz",
      "createdAt": "2026-01-24T16:35:13.015Z",
      "updatedAt": "2026-01-24T16:35:13.015Z"
    }
  },
  {
    "id": "cmksuiavj003711fc5wiibfnv",
    "name": "Kids Boys Clothing Product 1",
    "slug": "kids-boys-clothing-product-1",
    "description": "This is a high-quality Kids Boys Clothing Product 1 made from premium materials. Perfect for any occasion.",
    "categoryId": "cmksj68l9000tmmoxbcxff37h",
    "isFeatured": false,
    "isBestSeller": false,
    "isActive": true,
    "createdAt": "2026-01-24T21:52:32.143Z",
    "updatedAt": "2026-01-24T21:52:32.143Z",
    "basePrice": "1441",
    "isOffer": false,
    "artisanImage": null,
    "artisanStory": null,
    "careInstructions": null,
    "fabric": null,
    "occasion": null,
    "origin": null,
    "weave": null,
    "metaDescription": null,
    "metaTitle": null,
    "category": {
      "id": "cmksj68l9000tmmoxbcxff37h",
      "name": "Boys Clothing",
      "slug": "kids-boys-clothing",
      "description": "Boys Clothing for Kids",
      "image": null,
      "parentId": "cmksj68e1000rmmoxpjch39fk",
      "createdAt": "2026-01-24T16:35:13.532Z",
      "updatedAt": "2026-01-24T16:35:13.532Z"
    }
  },
  {
    "id": "cmksuibg4003g11fc0qsnyjuc",
    "name": "Kids Girls Clothing Product 1",
    "slug": "kids-girls-clothing-product-1",
    "description": "This is a high-quality Kids Girls Clothing Product 1 made from premium materials. Perfect for any occasion.",
    "categoryId": "cmksj68sh000vmmoxxz91cqky",
    "isFeatured": false,
    "isBestSeller": false,
    "isActive": true,
    "createdAt": "2026-01-24T21:52:32.883Z",
    "updatedAt": "2026-01-24T21:52:32.883Z",
    "basePrice": "659",
    "isOffer": false,
    "artisanImage": null,
    "artisanStory": null,
    "careInstructions": null,
    "fabric": null,
    "occasion": null,
    "origin": null,
    "weave": null,
    "metaDescription": null,
    "metaTitle": null,
    "category": {
      "id": "cmksj68sh000vmmoxxz91cqky",
      "name": "Girls Clothing",
      "slug": "kids-girls-clothing",
      "description": "Girls Clothing for Kids",
      "image": null,
      "parentId": "cmksj68e1000rmmoxpjch39fk",
      "createdAt": "2026-01-24T16:35:13.793Z",
      "updatedAt": "2026-01-24T16:35:13.793Z"
    }
  },
  {
    "id": "cmksuic10003p11fcx54fxpnd",
    "name": "Kids Infants Product 1",
    "slug": "kids-infants-product-1",
    "description": "This is a high-quality Kids Infants Product 1 made from premium materials. Perfect for any occasion.",
    "categoryId": "cmksj68zt000xmmox3c6duj7r",
    "isFeatured": false,
    "isBestSeller": false,
    "isActive": true,
    "createdAt": "2026-01-24T21:52:33.636Z",
    "updatedAt": "2026-01-24T21:52:33.636Z",
    "basePrice": "1048",
    "isOffer": false,
    "artisanImage": null,
    "artisanStory": null,
    "careInstructions": null,
    "fabric": null,
    "occasion": null,
    "origin": null,
    "weave": null,
    "metaDescription": null,
    "metaTitle": null,
    "category": {
      "id": "cmksj68zt000xmmox3c6duj7r",
      "name": "Infants",
      "slug": "kids-infants",
      "description": "Infants for Kids",
      "image": null,
      "parentId": "cmksj68e1000rmmoxpjch39fk",
      "createdAt": "2026-01-24T16:35:14.057Z",
      "updatedAt": "2026-01-24T16:35:14.057Z"
    }
  },
  {
    "id": "cmksuicn8003y11fccf32tg80",
    "name": "Kids School Uniforms Product 1",
    "slug": "kids-school-uniforms-product-1",
    "description": "This is a high-quality Kids School Uniforms Product 1 made from premium materials. Perfect for any occasion.",
    "categoryId": "cmksj6971000zmmox1mtfv7g1",
    "isFeatured": false,
    "isBestSeller": false,
    "isActive": true,
    "createdAt": "2026-01-24T21:52:34.435Z",
    "updatedAt": "2026-01-24T21:52:34.435Z",
    "basePrice": "1384",
    "isOffer": false,
    "artisanImage": null,
    "artisanStory": null,
    "careInstructions": null,
    "fabric": null,
    "occasion": null,
    "origin": null,
    "weave": null,
    "metaDescription": null,
    "metaTitle": null,
    "category": {
      "id": "cmksj6971000zmmox1mtfv7g1",
      "name": "School Uniforms",
      "slug": "kids-school-uniforms",
      "description": "School Uniforms for Kids",
      "image": null,
      "parentId": "cmksj68e1000rmmoxpjch39fk",
      "createdAt": "2026-01-24T16:35:14.317Z",
      "updatedAt": "2026-01-24T16:35:14.317Z"
    }
  },
  {
    "id": "cmksuiddv004811fcdpx9uo2q",
    "name": "Home Linen Bedsheets Product 1",
    "slug": "home-linen-bedsheets-product-1",
    "description": "This is a high-quality Home Linen Bedsheets Product 1 made from premium materials. Perfect for any occasion.",
    "categoryId": "cmksj69lv0012mmoxhhnz90vm",
    "isFeatured": false,
    "isBestSeller": true,
    "isActive": true,
    "createdAt": "2026-01-24T21:52:35.394Z",
    "updatedAt": "2026-01-24T21:52:35.394Z",
    "basePrice": "1405",
    "isOffer": false,
    "artisanImage": null,
    "artisanStory": null,
    "careInstructions": null,
    "fabric": null,
    "occasion": null,
    "origin": null,
    "weave": null,
    "metaDescription": null,
    "metaTitle": null,
    "category": {
      "id": "cmksj69lv0012mmoxhhnz90vm",
      "name": "Bedsheets",
      "slug": "home-linen-bedsheets",
      "description": "Bedsheets for Home Linen",
      "image": null,
      "parentId": "cmksj69em0010mmoxxmpphphk",
      "createdAt": "2026-01-24T16:35:14.851Z",
      "updatedAt": "2026-01-24T16:35:14.851Z"
    }
  },
  {
    "id": "cmksuidyf004h11fcyyzbkvuq",
    "name": "Home Linen Curtains Product 1",
    "slug": "home-linen-curtains-product-1",
    "description": "This is a high-quality Home Linen Curtains Product 1 made from premium materials. Perfect for any occasion.",
    "categoryId": "cmksj69t20014mmoxl8orsghe",
    "isFeatured": false,
    "isBestSeller": false,
    "isActive": true,
    "createdAt": "2026-01-24T21:52:36.134Z",
    "updatedAt": "2026-01-24T21:52:36.134Z",
    "basePrice": "1284",
    "isOffer": false,
    "artisanImage": null,
    "artisanStory": null,
    "careInstructions": null,
    "fabric": null,
    "occasion": null,
    "origin": null,
    "weave": null,
    "metaDescription": null,
    "metaTitle": null,
    "category": {
      "id": "cmksj69t20014mmoxl8orsghe",
      "name": "Curtains",
      "slug": "home-linen-curtains",
      "description": "Curtains for Home Linen",
      "image": null,
      "parentId": "cmksj69em0010mmoxxmpphphk",
      "createdAt": "2026-01-24T16:35:15.110Z",
      "updatedAt": "2026-01-24T16:35:15.110Z"
    }
  },
  {
    "id": "cmksuiekb004q11fcyp6cuox0",
    "name": "Home Linen Towels Product 1",
    "slug": "home-linen-towels-product-1",
    "description": "This is a high-quality Home Linen Towels Product 1 made from premium materials. Perfect for any occasion.",
    "categoryId": "cmksj6a0c0016mmox06d4x7p9",
    "isFeatured": false,
    "isBestSeller": true,
    "isActive": true,
    "createdAt": "2026-01-24T21:52:36.923Z",
    "updatedAt": "2026-01-24T21:52:36.923Z",
    "basePrice": "778",
    "isOffer": false,
    "artisanImage": null,
    "artisanStory": null,
    "careInstructions": null,
    "fabric": null,
    "occasion": null,
    "origin": null,
    "weave": null,
    "metaDescription": null,
    "metaTitle": null,
    "category": {
      "id": "cmksj6a0c0016mmox06d4x7p9",
      "name": "Towels",
      "slug": "home-linen-towels",
      "description": "Towels for Home Linen",
      "image": null,
      "parentId": "cmksj69em0010mmoxxmpphphk",
      "createdAt": "2026-01-24T16:35:15.372Z",
      "updatedAt": "2026-01-24T16:35:15.372Z"
    }
  },
  {
    "id": "cmksuif4e004z11fc4760cobq",
    "name": "Home Linen Blankets Product 1",
    "slug": "home-linen-blankets-product-1",
    "description": "This is a high-quality Home Linen Blankets Product 1 made from premium materials. Perfect for any occasion.",
    "categoryId": "cmksj6a7m0018mmox1g5t8nai",
    "isFeatured": false,
    "isBestSeller": true,
    "isActive": true,
    "createdAt": "2026-01-24T21:52:37.645Z",
    "updatedAt": "2026-01-25T10:28:35.066Z",
    "basePrice": "1126",
    "isOffer": false,
    "artisanImage": "[\"https://res.cloudinary.com/dtqetmk1c/image/upload/v1769336642/ahtdheze9m3bi7h5vauf.png\"]",
    "artisanStory": "",
    "careInstructions": "",
    "fabric": "",
    "occasion": null,
    "origin": "",
    "weave": "",
    "metaDescription": null,
    "metaTitle": null,
    "category": {
      "id": "cmksj6a7m0018mmox1g5t8nai",
      "name": "Blankets",
      "slug": "home-linen-blankets",
      "description": "Blankets for Home Linen",
      "image": null,
      "parentId": "cmksj69em0010mmoxxmpphphk",
      "createdAt": "2026-01-24T16:35:15.634Z",
      "updatedAt": "2026-01-24T16:35:15.634Z"
    }
  },
  {
    "id": "cmksuifov005811fcc7szcvdb",
    "name": "Home Linen Cushion Covers Product 1",
    "slug": "home-linen-cushion-covers-product-1",
    "description": "This is a high-quality Home Linen Cushion Covers Product 1 made from premium materials. Perfect for any occasion.",
    "categoryId": "cmksj6aev001ammoxhuwdiydv",
    "isFeatured": false,
    "isBestSeller": true,
    "isActive": true,
    "createdAt": "2026-01-24T21:52:38.382Z",
    "updatedAt": "2026-01-24T21:52:38.382Z",
    "basePrice": "2320",
    "isOffer": false,
    "artisanImage": null,
    "artisanStory": null,
    "careInstructions": null,
    "fabric": null,
    "occasion": null,
    "origin": null,
    "weave": null,
    "metaDescription": null,
    "metaTitle": null,
    "category": {
      "id": "cmksj6aev001ammoxhuwdiydv",
      "name": "Cushion Covers",
      "slug": "home-linen-cushion-covers",
      "description": "Cushion Covers for Home Linen",
      "image": null,
      "parentId": "cmksj69em0010mmoxxmpphphk",
      "createdAt": "2026-01-24T16:35:15.895Z",
      "updatedAt": "2026-01-24T16:35:15.895Z"
    }
  },
  {
    "id": "cmktxwdtt0001zl3fk2p3jvls",
    "name": "Kids Party Wear Set",
    "slug": "kids-party-wear-set-1769357714174",
    "description": "Elegant and comfortable party wear set for kids. Perfect for special occasions.",
    "categoryId": "cmksj68e1000rmmoxpjch39fk",
    "isFeatured": true,
    "isBestSeller": true,
    "isActive": true,
    "createdAt": "2026-01-25T16:15:14.177Z",
    "updatedAt": "2026-01-25T16:15:14.177Z",
    "basePrice": "1599",
    "isOffer": false,
    "artisanImage": null,
    "artisanStory": null,
    "careInstructions": null,
    "fabric": null,
    "occasion": null,
    "origin": null,
    "weave": null,
    "metaDescription": null,
    "metaTitle": null,
    "category": {
      "id": "cmksj68e1000rmmoxpjch39fk",
      "name": "Kids",
      "slug": "kids",
      "description": "All products for Kids",
      "image": null,
      "parentId": null,
      "createdAt": "2026-01-24T16:35:13.273Z",
      "updatedAt": "2026-01-24T16:35:13.273Z"
    }
  }
]